igm/__init__.py
igm/igm_run.py
igm/instructed_oggm.py
igm/common/__init__.py
igm/common/core/__init__.py
igm/common/core/src.py
igm/common/runner/__init__.py
igm/common/runner/configuration/__init__.py
igm/common/runner/configuration/loader.py
igm/common/runner/configuration/utils.py
igm/common/runner/modules/__init__.py
igm/common/runner/modules/loader.py
igm/common/runner/modules/src.py
igm/common/runner/modules/utils.py
igm/common/runner/modules/validator.py
igm/common/utilities/__init__.py
igm/common/utilities/misc.py
igm/common/utilities/printers.py
igm/common/utilities/visualizers.py
igm/conf/__init__.py
igm/conf/config.yaml
igm/conf/core.yaml
igm/conf/inputs/load_ncdf.yaml
igm/conf/inputs/load_tif.yaml
igm/conf/inputs/local.yaml
igm/conf/inputs/oggm_shop.yaml
igm/conf/outputs/local.yaml
igm/conf/outputs/plot2d.yaml
igm/conf/outputs/write_ncdf.yaml
igm/conf/outputs/write_tif.yaml
igm/conf/outputs/write_ts.yaml
igm/conf/outputs/write_vtp.yaml
igm/conf/processes/avalanche.yaml
igm/conf/processes/clim_glacialindex.yaml
igm/conf/processes/clim_oggm.yaml
igm/conf/processes/clim_station.yaml
igm/conf/processes/damage.yaml
igm/conf/processes/data_assimilation.yaml
igm/conf/processes/enthalpy.yaml
igm/conf/processes/flow_accumulation.yaml
igm/conf/processes/gflex.yaml
igm/conf/processes/glerosion.yaml
igm/conf/processes/iceflow.yaml
igm/conf/processes/particles.yaml
igm/conf/processes/pretraining.yaml
igm/conf/processes/read_output.yaml
igm/conf/processes/rockflow.yaml
igm/conf/processes/smb_accpdd.yaml
igm/conf/processes/smb_oggm.yaml
igm/conf/processes/smb_simple.yaml
igm/conf/processes/stress.yaml
igm/conf/processes/texture.yaml
igm/conf/processes/thk.yaml
igm/conf/processes/time.yaml
igm/conf/processes/vert_flow.yaml
igm/conf_help/__init__.py
igm/conf_help/core.yaml
igm/conf_help/header.yaml
igm/conf_help/inputs/load_ncdf.yaml
igm/conf_help/inputs/load_tif.yaml
igm/conf_help/inputs/local.yaml
igm/conf_help/inputs/oggm_shop.yaml
igm/conf_help/outputs/local.yaml
igm_model-3.1.0.dist-info/licenses/LICENSE
igm_model-3.1.0.dist-info/METADATA
igm_model-3.1.0.dist-info/WHEEL
igm_model-3.1.0.dist-info/entry_points.txt
igm_model-3.1.0.dist-info/top_level.txt
igm_model-3.1.0.dist-info/RECORD
